MANIFEST.in
README.rst
setup.py
docs/HISTORY.txt
docs/INSTALL.txt
docs/LICENSE.txt
ipnext/__init__.py
ipnext.site.editablefooter.egg-info/PKG-INFO
ipnext.site.editablefooter.egg-info/SOURCES.txt
ipnext.site.editablefooter.egg-info/dependency_links.txt
ipnext.site.editablefooter.egg-info/entry_points.txt
ipnext.site.editablefooter.egg-info/namespace_packages.txt
ipnext.site.editablefooter.egg-info/not-zip-safe
ipnext.site.editablefooter.egg-info/requires.txt
ipnext.site.editablefooter.egg-info/top_level.txt
ipnext/site/__init__.py
ipnext/site/editablefooter/__init__.py
ipnext/site/editablefooter/config.py
ipnext/site/editablefooter/configure.zcml
ipnext/site/editablefooter/testing.py
ipnext/site/editablefooter/tests.py
ipnext/site/editablefooter/Extensions/Install.py
ipnext/site/editablefooter/browser/__init__.py
ipnext/site/editablefooter/browser/configure.zcml
ipnext/site/editablefooter/browser/controlpanel.py
ipnext/site/editablefooter/browser/interfaces.py
ipnext/site/editablefooter/browser/viewlets.py
ipnext/site/editablefooter/browser/templates/footer.pt
ipnext/site/editablefooter/profiles/default/browserlayer.xml
ipnext/site/editablefooter/profiles/default/controlpanel.xml
ipnext/site/editablefooter/profiles/default/metadata.xml
ipnext/site/editablefooter/profiles/default/registry.xml
ipnext/site/editablefooter/profiles/default/viewlets.xml
ipnext/site/editablefooter/profiles/uninstall/viewlets.xml