Metadata-Version: 1.0
Name: ipnext.site.editablefooter
Version: 0.1.8
Summary: Edit the footer in the Plone Control Panel
Home-page: http://github.com/IPnext/
Author: zedr
Author-email: zedr@ipnext.it
License: GPL
Platform: UNKNOWN
Classifier: Framework :: Plone
Classifier: Programming Language :: Python
